metadataviewer/__init__.py
metadataviewer/__main__.py
metadataviewer/dao/__init__.py
metadataviewer/dao/numpy_dao.py
metadataviewer/dao/model/__init__.py
metadataviewer/gui/__init__.py
metadataviewer/gui/config.py
metadataviewer/gui/qt/__init__.py
metadataviewer/gui/qt/constants.py
metadataviewer/gui/qt/qtviewer.py
metadataviewer/gui/resources/apply_geometry.png
metadataviewer/gui/resources/backward-solid.png
metadataviewer/gui/resources/down-arrow.png
metadataviewer/gui/resources/error.png
metadataviewer/gui/resources/exit.png
metadataviewer/gui/resources/export_csv.png
metadataviewer/gui/resources/export_xlsx.png
metadataviewer/gui/resources/fa-arrow-down.png
metadataviewer/gui/resources/fa-arrow-up.png
metadataviewer/gui/resources/fa-cancel.png
metadataviewer/gui/resources/fa-close.png
metadataviewer/gui/resources/fa-list-ul.png
metadataviewer/gui/resources/fa-next.png
metadataviewer/gui/resources/fa-ok.png
metadataviewer/gui/resources/fa-previous.png
metadataviewer/gui/resources/folder.png
metadataviewer/gui/resources/from_here.png
metadataviewer/gui/resources/gallery.png
metadataviewer/gui/resources/goto_item.png
metadataviewer/gui/resources/hide.png
metadataviewer/gui/resources/image.png
metadataviewer/gui/resources/increasedecimals.png
metadataviewer/gui/resources/no-image.png
metadataviewer/gui/resources/plot.png
metadataviewer/gui/resources/plus.png
metadataviewer/gui/resources/preferences.png
metadataviewer/gui/resources/reducedecimals.png
metadataviewer/gui/resources/sections.png
metadataviewer/gui/resources/table-view.png
metadataviewer/gui/resources/table.png
metadataviewer/gui/resources/to_here.png
metadataviewer/gui/resources/up-arrow.png
metadataviewer/gui/resources/zoom.png
metadataviewer/model/__init__.py
metadataviewer/model/constants.py
metadataviewer/model/object_manager.py
metadataviewer/model/page.py
metadataviewer/model/renderers.py
metadataviewer/model/utils.py
metadataviewer/tests/__init__.py
metadata_viewer-2.5.dist-info/LICENSE
metadata_viewer-2.5.dist-info/METADATA
metadata_viewer-2.5.dist-info/WHEEL
metadata_viewer-2.5.dist-info/top_level.txt
metadata_viewer-2.5.dist-info/RECORD
