Metadata-Version: 2.1
Name: metadata-viewer
Version: 2.5
Summary: Generic metadata viewer
Author-email: Yunior Fonseca <cfonseca@cnb.csic.es>, Pablo Conesa <pconesa@cnb.csic.es>, Jorge Jiménez <jjimenez@cnb.csic.es>
License: GNU General Public License v3 (GPLv3)
Project-URL: Homepage, https://github.com/scipion-em/metadata-viewer
Project-URL: Repository, https://github.com/scipion-em/metadata-viewer
Project-URL: Issues, https://github.com/scipion-em/metadata-viewer/issues
Keywords: metadata-viewer
Requires-Python: >=3.8
License-File: LICENSE
Requires-Dist: pyqt5<=5.15.11
Requires-Dist: pillow==10.1.0
